pdf2img_cli/__init__.py
pdf2img_cli/__main__.py
pdf2img_cli/pdf2img.py
pdf2img_cli-0.1.0.dist-info/licenses/LICENSE
pdf2img_cli-0.1.0.dist-info/METADATA
pdf2img_cli-0.1.0.dist-info/WHEEL
pdf2img_cli-0.1.0.dist-info/entry_points.txt
pdf2img_cli-0.1.0.dist-info/top_level.txt
pdf2img_cli-0.1.0.dist-info/RECORD
