Metadata-Version: 2.4
Name: pdf2img-cli
Version: 0.1.0
Summary: command-line interface (CLI) to tranform pdf to images
Author-email: Darix Samani Siewe <samanidarix@gmail.com>
Requires-Python: >=3.13
License-File: LICENSE
Requires-Dist: pdf2image>=1.17.0
Dynamic: license-file
